parade_crossfilter/__init__.py
parade_crossfilter/urls.py
parade_crossfilter/views.py
parade_crossfilter/__pycache__/__init__.cpython-39.pyc
parade_crossfilter/__pycache__/urls.cpython-39.pyc
parade_crossfilter/__pycache__/views.cpython-39.pyc
parade_crossfilter/static/parade_crossfilter/css/2.1e4766ba.chunk.css
parade_crossfilter/static/parade_crossfilter/css/2.1e4766ba.chunk.css.map
parade_crossfilter/static/parade_crossfilter/css/main.c9b3bb0d.chunk.css
parade_crossfilter/static/parade_crossfilter/css/main.c9b3bb0d.chunk.css.map
parade_crossfilter/static/parade_crossfilter/js/2.21c7c5d7.chunk.js
parade_crossfilter/static/parade_crossfilter/js/2.21c7c5d7.chunk.js.map
parade_crossfilter/static/parade_crossfilter/js/main.9199da73.chunk.js
parade_crossfilter/static/parade_crossfilter/js/main.9199da73.chunk.js.map
parade_crossfilter/static/parade_crossfilter/js/runtime~main.b51ffc1e.js
parade_crossfilter/static/parade_crossfilter/js/runtime~main.b51ffc1e.js.map
parade_crossfilter/templates/parade_crossfilter/index.html
parade_crossfilter-0.0.5.dist-info/LICENSE
parade_crossfilter-0.0.5.dist-info/METADATA
parade_crossfilter-0.0.5.dist-info/WHEEL
parade_crossfilter-0.0.5.dist-info/top_level.txt
parade_crossfilter-0.0.5.dist-info/RECORD
