Metadata-Version: 2.1
Name: parade-crossfilter
Version: 0.0.5
Summary: OMERO.web plugin to test crossfilter
Home-page: UNKNOWN
Author: Will Moore
License: UNKNOWN
Keywords: OMERO.web,parade,crossfilter
Platform: UNKNOWN
Requires-Python: >=3
License-File: LICENSE
Requires-Dist: omero-web (>=5.6.1)
